src/__init__.py
src/main.py
src/webhook.py
src/opay/__init__.py
src/opay/express_checkout/__init__.py
src/opay/express_checkout/auth.py
src/opay/express_checkout/models.py
src/opay/express_checkout/opay_cashier.py
src/opay/serverAPI/__init__.py
src/utils/__init__.py
src/utils/constants.py
src/utils/custom_error.py
src/utils/helpers.py
test/__init__.py
test/test_opay_cashier.py
pyopay-0.1.0.dist-info/LICENSE
pyopay-0.1.0.dist-info/METADATA
pyopay-0.1.0.dist-info/WHEEL
pyopay-0.1.0.dist-info/top_level.txt
pyopay-0.1.0.dist-info/RECORD
