Metadata-Version: 2.2
Name: PyOpay
Version: 0.1.0
Summary: A client library for interacting with the Opay API
Home-page: https://github.com/Prevz26/Opay-py
Author: Precious Ojogu
Author-email: nkangprecious26@gmail.com
License: MIT
Classifier: Programming Language :: Python :: 3
Classifier: License :: OSI Approved :: MIT License
Classifier: Operating System :: OS Independent
Requires-Python: >=3.6
License-File: LICENSE
Requires-Dist: requests
Requires-Dist: pydantic
Dynamic: author
Dynamic: author-email
Dynamic: classifier
Dynamic: description
Dynamic: description-content-type
Dynamic: home-page
Dynamic: license
Dynamic: requires-dist
Dynamic: requires-python
Dynamic: summary
